swift/__init__.py
swift/account/__init__.py
swift/account/auditor.py
swift/account/backend.py
swift/account/reaper.py
swift/account/replicator.py
swift/account/server.py
swift/account/utils.py
swift/cli/__init__.py
swift/cli/account_audit.py
swift/cli/config.py
swift/cli/container_deleter.py
swift/cli/dispersion_populate.py
swift/cli/dispersion_report.py
swift/cli/drive_audit.py
swift/cli/form_signature.py
swift/cli/get_nodes.py
swift/cli/info.py
swift/cli/manage_shard_ranges.py
swift/cli/oldies.py
swift/cli/orphans.py
swift/cli/recon.py
swift/cli/recon_cron.py
swift/cli/reconciler_enqueue.py
swift/cli/relinker.py
swift/cli/reload.py
swift/cli/ring_builder_analyzer.py
swift/cli/ringbuilder.py
swift/cli/ringcomposer.py
swift/cli/shard-info.py
swift/common/__init__.py
swift/common/base_storage_server.py
swift/common/bufferedhttp.py
swift/common/constraints.py
swift/common/container_sync_realms.py
swift/common/daemon.py
swift/common/db.py
swift/common/db_auditor.py
swift/common/db_replicator.py
swift/common/digest.py
swift/common/direct_client.py
swift/common/error_limiter.py
swift/common/exceptions.py
swift/common/header_key_dict.py
swift/common/http.py
swift/common/http_protocol.py
swift/common/internal_client.py
swift/common/linkat.py
swift/common/manager.py
swift/common/memcached.py
swift/common/recon.py
swift/common/registry.py
swift/common/request_helpers.py
swift/common/splice.py
swift/common/statsd_client.py
swift/common/storage_policy.py
swift/common/swob.py
swift/common/wsgi.py
swift/common/middleware/__init__.py
swift/common/middleware/account_quotas.py
swift/common/middleware/acl.py
swift/common/middleware/backend_ratelimit.py
swift/common/middleware/bulk.py
swift/common/middleware/catch_errors.py
swift/common/middleware/cname_lookup.py
swift/common/middleware/container_quotas.py
swift/common/middleware/container_sync.py
swift/common/middleware/copy.py
swift/common/middleware/crossdomain.py
swift/common/middleware/dlo.py
swift-2.36.1.dist-info/licenses/AUTHORS
swift-2.36.1.dist-info/licenses/LICENSE
swift-2.36.1.dist-info/METADATA
swift-2.36.1.dist-info/WHEEL
swift-2.36.1.dist-info/entry_points.txt
swift-2.36.1.dist-info/pbr.json
swift-2.36.1.dist-info/top_level.txt
swift-2.36.1.dist-info/RECORD
