Metadata-Version: 2.4
Name: swift
Version: 2.36.1
Summary: OpenStack Object Storage
Home-page: https://docs.openstack.org/swift/latest/
Author: OpenStack
Author-email: openstack-discuss@lists.openstack.org
Project-URL: Documentation, https://docs.openstack.org/swift/latest/
Project-URL: Bug Tracker, https://bugs.launchpad.net/swift
Project-URL: Source Code, https://opendev.org/openstack/swift/
Project-URL: Release Notes, https://opendev.org/openstack/swift/src/branch/master/CHANGELOG
Classifier: Development Status :: 5 - Production/Stable
Classifier: Environment :: OpenStack
Classifier: Intended Audience :: Information Technology
Classifier: Intended Audience :: System Administrators
Classifier: License :: OSI Approved :: Apache Software License
Classifier: Operating System :: POSIX :: Linux
Classifier: Programming Language :: Python
Classifier: Programming Language :: Python :: 3
Classifier: Programming Language :: Python :: 3.7
Classifier: Programming Language :: Python :: 3.8
Classifier: Programming Language :: Python :: 3.9
Classifier: Programming Language :: Python :: 3.10
Classifier: Programming Language :: Python :: 3.11
Classifier: Programming Language :: Python :: 3.12
Requires-Python: >=3.7
License-File: LICENSE
License-File: AUTHORS
Requires-Dist: eventlet!=0.34.3,>=0.25.0
Requires-Dist: greenlet>=0.4.14
Requires-Dist: PasteDeploy>=2.0.0
Requires-Dist: lxml>=4.2.3
Requires-Dist: requests>=2.14.2
Requires-Dist: PyECLib!=1.6.2,!=1.6.3,>=1.3.1
Requires-Dist: cryptography>=2.0.2
Requires-Dist: dnspython>=1.15.0
Requires-Dist: xattr>=0.7.2; sys_platform != "win32"
Provides-Extra: kms-keymaster
Requires-Dist: oslo.config>=5.2.0; extra == "kms-keymaster"
Requires-Dist: castellan>=0.13.0; extra == "kms-keymaster"
Provides-Extra: kmip-keymaster
Requires-Dist: pykmip>=0.7.0; extra == "kmip-keymaster"
Provides-Extra: keystone
Requires-Dist: keystonemiddleware>=4.17.0; extra == "keystone"
Provides-Extra: test
Requires-Dist: hacking<7.1.0,>=2.0; extra == "test"
Requires-Dist: coverage>=5.2.1; extra == "test"
Requires-Dist: pytest>=4.6.11; extra == "test"
Requires-Dist: pytest-subtests>=0.3.0; extra == "test"
Requires-Dist: pytest-cov>=2.12.1; extra == "test"
Requires-Dist: stestr>=2.0.0; extra == "test"
Requires-Dist: python-swiftclient>=3.2.0; extra == "test"
Requires-Dist: python-keystoneclient>=3.19.0; extra == "test"
Requires-Dist: boto>=2.32.1; extra == "test"
Requires-Dist: boto3>=1.9; extra == "test"
Requires-Dist: botocore>=1.12; extra == "test"
Requires-Dist: requests-mock>=1.2.0; extra == "test"
Requires-Dist: keystonemiddleware>=4.17.0; extra == "test"
Requires-Dist: bandit>=1.1.0; extra == "test"
Requires-Dist: docutils>=0.15; extra == "test"
Dynamic: author
Dynamic: author-email
Dynamic: classifier
Dynamic: description
Dynamic: license-file
Dynamic: project-url
Dynamic: provides-extra
Dynamic: requires-dist
Dynamic: requires-python
Dynamic: summary
